{"type":"bubble","hero":{"type":"image","size":"full","aspectRatio":"20:13","aspectMode":"cover","url":"luck-pierot-goryokaku.jpg"},"body":{"type":"box","layout":"vertical","spacing":"sm","contents":[{"type":"text","text":"函館山展望台 山頂ショップ","wrap":true,"weight":"bold","size":"xl"},{"type":"box","layout":"vertical","contents":[{"type":"text","text":"10:00-21:00","wrap":true,"weight":"bold","size":"lg","flex":0},{"type":"text","gravity":"bottom","text":"函館山山頂にある展望台に併設されたお土産屋さん。","decoration":"none","wrap":true}]}]},"footer":{"type":"box","layout":"vertical","spacing":"sm","contents":[{"type":"button","style":"primary","action":{"type":"uri","label":"Check om Map","uri":"https://goo.gl/maps/x1sQmVzbePSAAjRK6"},"color":"#80abcf","gravity":"top"},{"type":"button","action":{"type":"postback","data":"hello","label":"Add to To do list"}}]}}